setup.py
crunchyroll/__init__.py
crunchyroll/constants.py
crunchyroll/models.py
crunchyroll/subtitles.py
crunchyroll/util.py
crunchyroll.egg-info/PKG-INFO
crunchyroll.egg-info/SOURCES.txt
crunchyroll.egg-info/dependency_links.txt
crunchyroll.egg-info/requires.txt
crunchyroll.egg-info/top_level.txt
crunchyroll/apis/__init__.py
crunchyroll/apis/ajax.py
crunchyroll/apis/android.py
crunchyroll/apis/errors.py
crunchyroll/apis/meta.py
crunchyroll/apis/scraper.py
tests/__init__.py
tests/test_integration.py