Metadata-Version: 1.1
Name: crunchyroll
Version: 1.0.1
Summary: A library to interface with Crunchyroll's various APIs and utilites to work
Home-page: https://github.com/aheadley/python-crunchyroll
Author: Alex Headley
Author-email: aheadley@waysaboutstuff.com
License: GPLv2.0
Platform: any
Classifier: Intended Audience :: Developers
Classifier: Natural Language :: English
Classifier: Programming Language :: Python
Classifier: Programming Language :: Python :: 2.6
Classifier: Programming Language :: Python :: 2.7
